ai_model_adapter/__init__.py
ai_model_adapter/cli.py
ai_model_adapter/model_adapter.py
ai_model_adapter-1.0.6.dist-info/licenses/LICENSE
ai_model_adapter-1.0.6.dist-info/METADATA
ai_model_adapter-1.0.6.dist-info/WHEEL
ai_model_adapter-1.0.6.dist-info/entry_points.txt
ai_model_adapter-1.0.6.dist-info/top_level.txt
ai_model_adapter-1.0.6.dist-info/RECORD
