Metadata-Version: 2.4
Name: ai-model-adapter
Version: 1.0.6
Summary: 一个简化的AI模型适配器，支持文本聊天、图像识别和图片生成功能
Home-page: https://github.com/itshen/ai_adapter
Author: 洛小山
Author-email: 洛小山 <eason@miyang.ai>
License: MIT
Project-URL: Homepage, https://github.com/itshen/ai_adapter
Project-URL: Documentation, https://github.com/itshen/ai_adapter#readme
Project-URL: Repository, https://github.com/itshen/ai_adapter
Project-URL: Bug Tracker, https://github.com/itshen/ai_adapter/issues
Keywords: ai,llm,chatbot,image-generation,image-recognition,vision,api-adapter
Classifier: Development Status :: 4 - Beta
Classifier: Intended Audience :: Developers
Classifier: License :: OSI Approved :: MIT License
Classifier: Operating System :: OS Independent
Classifier: Programming Language :: Python :: 3
Classifier: Programming Language :: Python :: 3.8
Classifier: Programming Language :: Python :: 3.9
Classifier: Programming Language :: Python :: 3.10
Classifier: Programming Language :: Python :: 3.11
Classifier: Programming Language :: Python :: 3.12
Classifier: Topic :: Software Development :: Libraries :: Python Modules
Classifier: Topic :: Scientific/Engineering :: Artificial Intelligence
Requires-Python: >=3.8
License-File: LICENSE
Requires-Dist: fastapi>=0.104.0
Requires-Dist: uvicorn>=0.24.0
Requires-Dist: httpx>=0.25.0
Requires-Dist: pydantic>=2.5.0
Requires-Dist: python-dotenv>=1.0.0
Provides-Extra: dev
Requires-Dist: pytest>=7.0.0; extra == "dev"
Requires-Dist: pytest-asyncio>=0.21.0; extra == "dev"
Requires-Dist: black>=23.0.0; extra == "dev"
Requires-Dist: flake8>=6.0.0; extra == "dev"
Requires-Dist: mypy>=1.0.0; extra == "dev"
Provides-Extra: test
Requires-Dist: pytest>=7.0.0; extra == "test"
Requires-Dist: pytest-asyncio>=0.21.0; extra == "test"
Requires-Dist: pytest-cov>=4.0.0; extra == "test"
Dynamic: author
Dynamic: home-page
Dynamic: license-file
Dynamic: requires-python
